plisio/__init__.py
plisio/plisio_client.py
plisio/plisio_enums.py
plisio/plisio_exceptions.py
plisio/plisio_models.py
plisio-1.0.11.dist-info/licenses/LICENSE.txt
plisio-1.0.11.dist-info/METADATA
plisio-1.0.11.dist-info/WHEEL
plisio-1.0.11.dist-info/top_level.txt
plisio-1.0.11.dist-info/RECORD
