Metadata-Version: 2.4
Name: plisio
Version: 1.0.11
Summary: Official Python SDK for Plisio API
Home-page: https://github.com/Plisio/plisio-python
Download-URL: https://github.com/Plisio/plisio-python
Author: Plisio
Author-email: support@plisio.net
License: MIT
Keywords: plisio,crypto payment,sdk,bitcoin,etherium,crypto,blockchain
Classifier: Development Status :: 5 - Production/Stable
Classifier: Topic :: Software Development :: Build Tools
Classifier: License :: OSI Approved :: MIT License
Classifier: Programming Language :: Python :: 3
Classifier: Programming Language :: Python :: 3.6
Classifier: Programming Language :: Python :: 3.7
Classifier: Programming Language :: Python :: 3.8
Classifier: Programming Language :: Python :: 3.9
Classifier: Programming Language :: Python :: 3.10
Classifier: Programming Language :: Python :: 3.11
Classifier: Programming Language :: Python :: 3.12
Classifier: Programming Language :: Python :: 3.13
License-File: LICENSE.txt
Requires-Dist: aiohttp
Requires-Dist: requests
Requires-Dist: hashlib; python_version <= "3.9"
Requires-Dist: hmac; python_version <= "3.9"
Dynamic: author
Dynamic: author-email
Dynamic: classifier
Dynamic: description
Dynamic: description-content-type
Dynamic: download-url
Dynamic: home-page
Dynamic: keywords
Dynamic: license
Dynamic: license-file
Dynamic: requires-dist
Dynamic: summary
